{
  "$type": "ConfigMonster",
  "common": {
    "$type": "ConfigEntityCommon",
    "effectAttachShape": {
      "$type": "ConfigEffectAttachSkinnedMesh",
      "mesh": "EffectMesh"
    },
    "mass": 30,
    "affectedByWorld": true,
    "checkInSurface": true,
    "scale": 1.1,
    "useGrassDisplacement": true
  },
  "headControl": {
    "$type": "ConfigHeadControl",
    "useHeadControl": true,
    "animStates": [
      "NormalIdle/Standby",
      "NormalMove/WalkForward",
      "NormalMove/WalkBack",
      "NormalMove/WalkRight",
      "NormalMove/WalkLeft",
      "NormalMove/Run",
      "Turn/TurnLeft",
      "Turn/TurnRight"
    ]
  },
  "model": {
    "$type": "ConfigModel",
    "bornEffect": "Monster_Common_Born"
  },
  "combat": {
    "$type": "ConfigCombat",
    "property": {
      "$type": "ConfigCombatProperty",
      "endureType": "Monster_Minion",
      "lockShape": "CircleLockEnemy",
      "weight": 75
    },
    "beHit": {
      "$type": "ConfigCombatBeHit"
    },
    "die": {
      "$type": "ConfigDie",
      "hasAnimatorDie": true,
      "dieEndTime": 1,
      "dieForceDisappearTime": 4,
      "dieDisappearEffect": "Death_Common",
      "dieDisappearEffectDelay": 1,
      "dieShaderData": "MonsterDie",
      "useRagDoll": true,
      "ragDollDieEndTimeDelay": 1.25
    },
    "animEvents": {
      "AtkL01": {
        "$type": "ConfigAttackEvent",
        "attackPattern": {
          "$type": "ConfigAttackCircle",
          "triggerType": "TriggerNoRepeat",
          "scale": 1,
          "offsetZ": -0.5,
          "fanAngle": 75,
          "radius": 2
        },
        "attackInfo": {
          "$type": "ConfigAttackInfo",
          "attackProperty": {
            "$type": "ConfigAttackProperty",
            "damagePercentage": 1,
            "damagePercentageRatio": 0,
            "elementDurability": 100,
            "strikeType": "Blunt",
            "enBreak": 50,
            "attackType": "Melee"
          },
          "hitPattern": {
            "$type": "ConfigHitPattern",
            "onHitEffectName": "default",
            "hitLevel": "Light",
            "hitImpulseX": 200,
            "hitImpulseY": 0
          }
        }
      },
      "AtkL02": {
        "$type": "ConfigAttackEvent",
        "attackPattern": {
          "$type": "ConfigAttackCircle",
          "triggerType": "TriggerNoRepeat",
          "scale": 1,
          "offsetZ": -0.5,
          "fanAngle": 75,
          "radius": 2
        },
        "attackInfo": {
          "$type": "ConfigAttackInfo",
          "attackProperty": {
            "$type": "ConfigAttackProperty",
            "damagePercentage": 1,
            "damagePercentageRatio": 0,
            "elementDurability": 100,
            "strikeType": "Blunt",
            "enBreak": 50,
            "attackType": "Melee"
          },
          "hitPattern": {
            "$type": "ConfigHitPattern",
            "onHitEffectName": "default",
            "hitLevel": "Light",
            "hitImpulseX": 200,
            "hitImpulseY": 0
          }
        }
      },
      "AtkL03": {
        "$type": "ConfigAttackEvent",
        "attackPattern": {
          "$type": "ConfigAttackCircle",
          "triggerType": "TriggerNoRepeat",
          "scale": 1,
          "offsetZ": -0.5,
          "fanAngle": 75,
          "radius": 2
        },
        "attackInfo": {
          "$type": "ConfigAttackInfo",
          "attackProperty": {
            "$type": "ConfigAttackProperty",
            "damagePercentage": 1.25,
            "damagePercentageRatio": 0,
            "elementDurability": 100,
            "strikeType": "Blunt",
            "enBreak": 100,
            "attackType": "Melee"
          },
          "hitPattern": {
            "$type": "ConfigHitPattern",
            "onHitEffectName": "default",
            "hitLevel": "Heavy",
            "hitImpulseX": 800,
            "hitImpulseY": 0
          },
          "cameraShake": {
            "$type": "ConfigCameraShake",
            "shakeType": "HitVector",
            "shakeRange": 0.04,
            "shakeTime": 0.09,
            "shakeDir": {
              "$type": "Vector",
              "y": -1
            }
          }
        }
      },
      "AtkH": {
        "$type": "ConfigAttackEvent",
        "attackPattern": {
          "$type": "ConfigAttackCircle",
          "triggerType": "TriggerNoRepeat",
          "scale": 1,
          "offsetZ": -0.5,
          "fanAngle": 75,
          "radius": 1.75
        },
        "attackInfo": {
          "$type": "ConfigAttackInfo",
          "attackProperty": {
            "$type": "ConfigAttackProperty",
            "damagePercentage": 2,
            "damagePercentageRatio": 0,
            "elementDurability": 100,
            "strikeType": "Blunt",
            "enBreak": 200,
            "attackType": "Melee"
          },
          "hitPattern": {
            "$type": "ConfigHitPattern",
            "onHitEffectName": "default",
            "hitLevel": "Air",
            "hitImpulseX": 480,
            "hitImpulseY": 600
          },
          "cameraShake": {
            "$type": "ConfigCameraShake",
            "shakeType": "HitVector",
            "shakeRange": 0.06,
            "shakeTime": 0.09,
            "shakeDir": {
              "$type": "Vector",
              "y": -1
            }
          }
        }
      },
      "AtkNormal": {
        "$type": "ConfigAttackEvent",
        "attackPattern": {
          "$type": "ConfigAttackCircle",
          "triggerType": "TriggerNoRepeat",
          "scale": 1,
          "fanAngle": 60,
          "radius": 1.75
        },
        "attackInfo": {
          "$type": "ConfigAttackInfo",
          "attackProperty": {
            "$type": "ConfigAttackProperty",
            "damagePercentage": 1,
            "damagePercentageRatio": 0,
            "elementDurability": 100,
            "strikeType": "Blunt",
            "enBreak": 80,
            "attackType": "Melee"
          },
          "hitPattern": {
            "$type": "ConfigHitPattern",
            "onHitEffectName": "default",
            "hitLevel": "Heavy",
            "hitImpulseX": 200,
            "hitImpulseY": 0,
            "hitHaltTimeScale": 0.01
          }
        }
      },
      "AtkNo": {
        "$type": "ConfigAttackEvent",
        "attackPattern": {
          "$type": "ConfigAttackCircle",
          "triggerType": "TriggerNoRepeat",
          "scale": 1,
          "offsetZ": -0.5,
          "fanAngle": 60,
          "radius": 1.5
        },
        "attackInfo": {
          "$type": "ConfigAttackInfo",
          "attackProperty": {
            "$type": "ConfigAttackProperty",
            "damagePercentage": 0.75,
            "damagePercentageRatio": 0,
            "elementDurability": 100,
            "strikeType": "Blunt",
            "enBreak": 60,
            "attackType": "Melee"
          },
          "hitPattern": {
            "$type": "ConfigHitPattern",
            "onHitEffectName": "default",
            "hitLevel": "Heavy",
            "hitImpulseX": 200,
            "hitImpulseY": 0,
            "hitHaltTimeScale": 0.01
          }
        }
      },
      "DefendAttack_BS": {
        "$type": "ConfigAttackEvent",
        "attackPattern": {
          "$type": "ConfigAttackCircle",
          "triggerType": "TriggerNoRepeat",
          "scale": 1,
          "fanAngle": 120,
          "radius": 1.5,
          "offsetAngle": -30
        },
        "attackInfo": {
          "$type": "ConfigAttackInfo",
          "attackProperty": {
            "$type": "ConfigAttackProperty",
            "damagePercentage": 0,
            "damagePercentageRatio": 0,
            "elementDurability": 100,
            "enBreak": 60
          },
          "hitPattern": {
            "$type": "ConfigHitPattern",
            "onHitEffectName": "default",
            "hitLevel": "Heavy",
            "hitImpulseX": 200,
            "hitImpulseY": 0,
            "hitHaltTime": 0.12,
            "hitHaltTimeScale": 0.1,
            "muteHitText": true
          }
        }
      },
      "DefendAttack_AS": {
        "$type": "ConfigAttackEvent",
        "attackPattern": {
          "$type": "ConfigAttackCircle",
          "triggerType": "TriggerNoRepeat",
          "scale": 1,
          "offsetZ": -0.5,
          "fanAngle": 75,
          "radius": 2
        },
        "attackInfo": {
          "$type": "ConfigAttackInfo",
          "attackProperty": {
            "$type": "ConfigAttackProperty",
            "damagePercentage": 1,
            "damagePercentageRatio": 0,
            "elementDurability": 100,
            "strikeType": "Blunt",
            "enBreak": 60,
            "attackType": "Melee"
          },
          "hitPattern": {
            "$type": "ConfigHitPattern",
            "onHitEffectName": "default",
            "hitLevel": "Heavy",
            "hitImpulseX": 800,
            "hitImpulseY": 0
          }
        }
      }
    }
  },
  "equipController": {
    "$type": "ConfigEquipController",
    "attachPoints": {
      "equip01": "WeaponR",
      "equip02": "WeaponL"
    }
  },
  "abilities": [
    {
      "$type": "ConfigEntityAbilityEntry",
      "abilityID": "Alert",
      "abilityName": "Hili_None_Alert"
    },
    {
      "$type": "ConfigEntityAbilityEntry",
      "abilityID": "SteerAttack",
      "abilityName": "Hili_None_SteerAttack"
    },
    {
      "$type": "ConfigEntityAbilityEntry",
      "abilityID": "Shoot",
      "abilityName": "Hili_None_ShootArrow_WithRandom"
    },
    {
      "$type": "ConfigEntityAbilityEntry",
      "abilityID": "ThrowPebble_Effect",
      "abilityName": "Hili_None_ThrowPebble_Effect"
    },
    {
      "$type": "ConfigEntityAbilityEntry",
      "abilityID": "ThrowPebble",
      "abilityName": "Hili_None_ThrowPebble"
    },
    {
      "$type": "ConfigEntityAbilityEntry",
      "abilityID": "ThrowPebble_Shield_Effect",
      "abilityName": "Hili_None_ThrowPebble_Shield_Effect"
    },
    {
      "$type": "ConfigEntityAbilityEntry",
      "abilityID": "ThrowPebble_Shield",
      "abilityName": "Hili_None_ThrowPebble_Shield"
    },
    {
      "$type": "ConfigEntityAbilityEntry",
      "abilityID": "TurnToSleep",
      "abilityName": "Hili_None_TurnToSleep"
    },
    {
      "$type": "ConfigEntityAbilityEntry",
      "abilityID": "OutOfSleep",
      "abilityName": "Hili_None_OutOfSleep"
    },
    {
      "$type": "ConfigEntityAbilityEntry",
      "abilityID": "TurnToSit",
      "abilityName": "Hili_None_TurnToSit"
    },
    {
      "$type": "ConfigEntityAbilityEntry",
      "abilityID": "OutOfSit",
      "abilityName": "Hili_None_OutOfSit"
    },
    {
      "$type": "ConfigEntityAbilityEntry",
      "abilityID": "AwakeAlert",
      "abilityName": "Hili_None_AwakeAlert"
    },
    {
      "$type": "ConfigEntityAbilityEntry",
      "abilityID": "Hili_None_SpecialsState_Weapon",
      "abilityName": "Hili_None_SpecialsState_Weapon"
    },
    {
      "$type": "ConfigEntityAbilityEntry",
      "abilityID": "SpecialsState_AIStateInitial",
      "abilityName": "Hili_None_SpecialsState_AIStateInitial"
    }
  ],
  "stateLayers": {
    "defaultLayer": {
      "$type": "ConfigNormalStateLayer",
      "stateIDs": {
        "NormalIdle": {
          "$type": "ConfigMonsterStateIDInfo",
          "animatorStates": {
            "Standby": [],
            "Born": []
          },
          "canDoSkill": true,
          "canSyncMove": true,
          "resetAnimatorTriggerOnExit": [
            "DoSkill"
          ]
        },
        "NormalMove": {
          "$type": "ConfigMonsterStateIDInfo",
          "animatorStates": {
            "WalkForward": [
              "Audio_Hili_Walk"
            ],
            "WalkBack": [
              "Audio_Hili_Walk"
            ],
            "WalkRight": [
              "Audio_Hili_Walk"
            ],
            "WalkLeft": [
              "Audio_Hili_Walk"
            ],
            "Run": [
              "Audio_Hili_Run"
            ]
          },
          "canDoSkill": true,
          "canSyncMove": true,
          "resetAnimatorTriggerOnExit": [
            "DoSkill"
          ],
          "canSteer": true
        },
        "Turn": {
          "$type": "ConfigMonsterStateIDInfo",
          "animatorStates": {
            "TurnLeft": [
              "Audio_Hili_Walk"
            ],
            "TurnRight": [
              "Audio_Hili_Walk"
            ]
          },
          "canDoSkill": true,
          "canSyncMove": true,
          "resetAnimatorTriggerOnExit": [
            "DoSkill"
          ],
          "canSteer": true,
          "autoSteer": true
        },
        "Sleep": {
          "$type": "ConfigMonsterStateIDInfo",
          "animatorStates": {
            "Sleep": [
              "Audio_Hili_Sleep"
            ]
          },
          "canDoSkill": true,
          "canSyncMove": true,
          "resetAnimatorTriggerOnExit": [
            "DoSkill"
          ]
        },
        "Sit": {
          "$type": "ConfigMonsterStateIDInfo",
          "animatorStates": {
            "Sit": []
          },
          "canDoSkill": true,
          "canSyncMove": true,
          "resetAnimatorTriggerOnExit": [
            "DoSkill"
          ]
        },
        "WeaponOnFire": {
          "$type": "ConfigMonsterStateIDInfo",
          "animatorStates": {
            "WeaponOnFire": [
              "Audio_Hili_WeaponOnFire"
            ]
          },
          "canSyncMove": true,
          "resetAnimatorTriggerOnExit": [
            "DoSkill"
          ]
        },
        "BeHit": {
          "$type": "ConfigMonsterStateIDInfo",
          "animatorStates": {
            "Hit_L": [
              "Audio_Hili_Hit_L"
            ],
            "Hit_H": [
              "Audio_Hili_Hit_H"
            ],
            "DHit": [
              "Audio_Hili_Hit_L"
            ]
          },
          "resetAnimatorTriggerOnEnter": [
            "BeHit"
          ],
          "resetAnimatorTriggerOnExit": [
            "DoSkill"
          ]
        },
        "BeHitThrow": {
          "$type": "ConfigMonsterStateIDInfo",
          "animatorStates": {
            "HitThrow": [
              "Audio_Hili_Hit_Throw"
            ],
            "HitThrowDrop": [],
            "HitThrowToGround": [
              "Audio_Hili_Hit_ThrowToGround"
            ]
          },
          "resetAnimatorTriggerOnEnter": [
            "BeHit",
            "HitAir2HitDrop"
          ],
          "resetAnimatorTriggerOnExit": [
            "DoSkill"
          ]
        },
        "Struggle": {
          "$type": "ConfigMonsterStateIDInfo",
          "animatorStates": {
            "Struggle": []
          },
          "resetAnimatorTriggerOnEnter": [
            "BeHit",
            "HitAir2HitDrop"
          ],
          "resetAnimatorTriggerOnExit": [
            "DoSkill"
          ]
        },
        "Die": {
          "$type": "ConfigMonsterStateIDInfo",
          "animatorStates": {
            "SwimDie": [
              "Monster_Hili_None_Die",
              "Audio_Hili_SwimDie"
            ],
            "SwimDie_AS": [
              "Audio_Hili_SwimDie"
            ]
          }
        },
        "Die_RagDoll": {
          "$type": "ConfigMonsterStateIDInfo",
          "animatorStates": {
            "Die1": [
              "Monster_Hili_None_Die",
              "Audio_Hili_Die1"
            ],
            "Die2": [
              "Monster_Hili_None_Die",
              "Audio_Hili_Die2"
            ],
            "AirDie": [
              "Monster_Hili_None_Die",
              "Audio_Hili_Die1"
            ]
          },
          "enableRagDoll": true
        },
        "TurnToSleep": {
          "$type": "ConfigMonsterStateIDInfo",
          "animatorStates": {
            "TurnToSleep": [
              "Monster_Hili_None_TurnToSleep"
            ]
          },
          "canDoSkill": true,
          "resetAnimatorTriggerOnExit": [
            "BeHit",
            "DoSkill"
          ]
        },
        "OutOfSleep": {
          "$type": "ConfigMonsterStateIDInfo",
          "animatorStates": {
            "OutOfSleep": [
              "Monster_Hili_None_OutOfSleep"
            ]
          },
          "canDoSkill": true,
          "resetAnimatorTriggerOnExit": [
            "BeHit",
            "DoSkill"
          ]
        },
        "TurnToSit": {
          "$type": "ConfigMonsterStateIDInfo",
          "animatorStates": {
            "TurnToSit": [
              "Monster_Hili_None_TurnToSit"
            ]
          },
          "canDoSkill": true,
          "resetAnimatorTriggerOnExit": [
            "BeHit",
            "DoSkill"
          ]
        },
        "OutOfSit": {
          "$type": "ConfigMonsterStateIDInfo",
          "animatorStates": {
            "OutOfSit": [
              "Monster_Hili_None_OutOfSit"
            ]
          },
          "canDoSkill": true,
          "resetAnimatorTriggerOnExit": [
            "BeHit",
            "DoSkill"
          ]
        },
        "Life_Alert": {
          "$type": "ConfigMonsterStateIDInfo",
          "animatorStates": {
            "Alert": []
          },
          "resetAnimatorTriggerOnExit": [
            "BeHit",
            "DoSkill"
          ]
        },
        "Life_Warning": {
          "$type": "ConfigMonsterStateIDInfo",
          "animatorStates": {
            "Warning": [
              "Monster_Undead01_Warning",
              "Monster_Hili_None_Alert",
              "Audio_Hili_Warning"
            ]
          },
          "resetAnimatorTriggerOnExit": [
            "BeHit",
            "DoSkill"
          ]
        },
        "Life_Talk": {
          "$type": "ConfigMonsterStateIDInfo",
          "animatorStates": {
            "Talk": [],
            "Talk_Sit": []
          },
          "canDoSkill": true,
          "resetAnimatorTriggerOnExit": [
            "BeHit",
            "DoSkill"
          ]
        },
        "SleepFree01": {
          "$type": "ConfigMonsterStateIDInfo",
          "animatorStates": {
            "SleepFree01": []
          },
          "canDoSkill": true,
          "resetAnimatorTriggerOnExit": [
            "BeHit",
            "DoSkill"
          ]
        },
        "SleepFree02": {
          "$type": "ConfigMonsterStateIDInfo",
          "animatorStates": {
            "SleepFree02": []
          },
          "canDoSkill": true,
          "resetAnimatorTriggerOnExit": [
            "BeHit",
            "DoSkill"
          ]
        },
        "SleepFree03": {
          "$type": "ConfigMonsterStateIDInfo",
          "animatorStates": {
            "SleepFree03": []
          },
          "canDoSkill": true,
          "resetAnimatorTriggerOnExit": [
            "BeHit",
            "DoSkill"
          ]
        },
        "SitFree01": {
          "$type": "ConfigMonsterStateIDInfo",
          "animatorStates": {
            "SitFree01": []
          },
          "canDoSkill": true,
          "resetAnimatorTriggerOnExit": [
            "BeHit",
            "DoSkill"
          ]
        },
        "Life_AwakeAlertBS": {
          "$type": "ConfigMonsterStateIDInfo",
          "animatorStates": {
            "AwakeAlert_BS": [
              "Monster_Hili_None_AwakeAlert"
            ]
          },
          "resetAnimatorTriggerOnExit": [
            "BeHit",
            "DoSkill",
            "AwakeAlert"
          ]
        },
        "Life_AwakeAlertAS": {
          "$type": "ConfigMonsterStateIDInfo",
          "animatorStates": {
            "AwakeAlert_AS": []
          },
          "canDoSkill": true,
          "resetAnimatorTriggerOnExit": [
            "BeHit",
            "DoSkill"
          ]
        },
        "Sword_TripleAttack": {
          "$type": "ConfigMonsterStateIDInfo",
          "animatorStates": {
            "Sword_TripleAttack_First_BS": [
              "Monster_Undead01_TripleAttack_First"
            ],
            "Sword_TripleAttack_First_Halt": [
              "Monster_Undead01_TripleAttack_First"
            ],
            "Sword_TripleAttack_First": [
              "Monster_Undead01_TripleAttack_First",
              "Audio_Hili_TripleAtk_01",
              "Audio_Hili_TripleAtk"
            ],
            "Sword_TripleAttack_Second_Halt": [
              "Monster_Undead01_TripleAttack_Second"
            ],
            "Sword_TripleAttack_Second": [
              "Monster_Undead01_TripleAttack_Second",
              "Audio_Hili_TripleAtk_01"
            ],
            "Sword_TripleAttack_Thrid_Halt": [
              "Monster_Undead01_TripleAttack_Thrid"
            ],
            "Sword_TripleAttack_Thrid": [
              "Monster_Undead01_TripleAttack_Thrid",
              "Audio_Hili_TripleAtk_02"
            ]
          },
          "resetAnimatorTriggerOnExit": [
            "BeHit",
            "DoSkill"
          ]
        },
        "Sword_ThumpAttack": {
          "$type": "ConfigMonsterStateIDInfo",
          "animatorStates": {
            "Sword_ThumpAttack_BS": [
              "Monster_Undead01_ThumpAttack",
              "Audio_Hili_ThumpAtk"
            ],
            "Sword_ThumpAttack_Halt": [
              "Monster_Undead01_ThumpAttack"
            ],
            "Sword_ThumpAttack": [
              "Monster_Undead01_ThumpAttack",
              "Audio_Hili_Sword_ThumpAttack"
            ]
          },
          "addEndure": 0.6,
          "resetAnimatorTriggerOnExit": [
            "BeHit",
            "DoSkill"
          ]
        },
        "Sword_NormalAttack": {
          "$type": "ConfigMonsterStateIDInfo",
          "animatorStates": {
            "Sword_NormalAttack": [
              "Monster_Hili_None_NormalAttack",
              "Audio_Hili_Sword_NormalAtk"
            ]
          },
          "resetAnimatorTriggerOnExit": [
            "BeHit",
            "DoSkill"
          ]
        },
        "NoWeapon_Attack": {
          "$type": "ConfigMonsterStateIDInfo",
          "animatorStates": {
            "NoWeapon_Attack": [
              "Monster_Hili_None_NoWeaponAttack",
              "Audio_Hili_NormalAtk"
            ]
          },
          "resetAnimatorTriggerOnExit": [
            "BeHit",
            "DoSkill"
          ]
        },
        "PickUp": {
          "$type": "ConfigMonsterStateIDInfo",
          "animatorStates": {
            "PickUp": [
              "Monster_Undead01_PickUp"
            ]
          },
          "resetAnimatorTriggerOnExit": [
            "BeHit",
            "DoSkill"
          ]
        },
        "Taunt": {
          "$type": "ConfigMonsterStateIDInfo",
          "animatorStates": {
            "Taunt_1": [
              "Audio_Hili_Taunt"
            ],
            "Taunt_2": [
              "Audio_Hili_Taunt"
            ],
            "Taunt_3": [
              "Audio_Hili_Taunt"
            ]
          },
          "resetAnimatorTriggerOnExit": [
            "BeHit",
            "DoSkill"
          ]
        },
        "Taunt_NoWeapon": {
          "$type": "ConfigMonsterStateIDInfo",
          "animatorStates": {
            "Taunt_NoWeapon_1": [
              "Audio_Hili_Taunt"
            ],
            "Taunt_NoWeapon_2": [
              "Audio_Hili_Taunt"
            ]
          },
          "resetAnimatorTriggerOnExit": [
            "BeHit",
            "DoSkill"
          ]
        },
        "Aim": {
          "$type": "ConfigMonsterStateIDInfo",
          "animatorStates": {
            "Aim": []
          },
          "resetAnimatorTriggerOnExit": [
            "BeHit",
            "DoSkill"
          ]
        },
        "Shoot": {
          "$type": "ConfigMonsterStateIDInfo",
          "animatorStates": {
            "Attack": [
              "Monster_Hili_Grass_Shoot_WithRandom",
              "Audio_Hili_Shoot_Atk"
            ]
          },
          "resetAnimatorTriggerOnExit": [
            "BeHit",
            "DoSkill"
          ]
        },
        "Dodge": {
          "$type": "ConfigMonsterStateIDInfo",
          "animatorStates": {
            "Dodge": [
              "Audio_Hili_Crossbow_Dodge"
            ]
          },
          "resetAnimatorTriggerOnExit": [
            "BeHit",
            "DoSkill",
            "DodgeTrigger"
          ]
        },
        "Defend": {
          "$type": "ConfigMonsterStateIDInfo",
          "animatorStates": {
            "Defend": [
              "Audio_Hili_DefendAtk_Defend"
            ]
          },
          "resetAnimatorTriggerOnEnter": [
            "DefendTrigger"
          ],
          "resetAnimatorTriggerOnExit": [
            "BeHit",
            "DoSkill"
          ]
        },
        "DefendAttack": {
          "$type": "ConfigMonsterStateIDInfo",
          "animatorStates": {
            "DefendAttack_BS": [
              "Monster_Hili_None_DefendAttack_BS",
              "Audio_Hili_DefendAtk_BS"
            ],
            "DefendAttack_AS": [
              "Monster_Hili_None_DefendAttack_AS",
              "Audio_Hili_DefendAtk_AS"
            ]
          },
          "addEndure": 0.6,
          "resetAnimatorTriggerOnEnter": [
            "DefendAttackTrigger"
          ],
          "resetAnimatorTriggerOnExit": [
            "BeHit",
            "DoSkill"
          ]
        },
        "ThrowPebble": {
          "$type": "ConfigMonsterStateIDInfo",
          "animatorStates": {
            "ThrowPebble": [
              "Monster_Hili_None_ThrowPebble",
              "Audio_Hili_ThrowPebble"
            ]
          },
          "massRatio": 100,
          "resetAnimatorTriggerOnExit": [
            "BeHit",
            "DoSkill"
          ]
        },
        "ThrowPebble_Shield": {
          "$type": "ConfigMonsterStateIDInfo",
          "animatorStates": {
            "ThrowPebble_Shield": [
              "Monster_Hili_None_ThrowPebble_Shield"
            ]
          },
          "massRatio": 100,
          "resetAnimatorTriggerOnExit": [
            "BeHit",
            "DoSkill"
          ]
        }
      }
    }
  },
  "billboard": {
    "$type": "ConfigCombatBillboard",
    "attachPoint": "BillboardAttach",
    "offset": {
      "$type": "Vector",
      "y": 0.35,
      "z": 0.05
    },
    "depthOffset": 0.3,
    "showHPBar": true
  },
  "initialPoses": {
    "Defalut": {
      "$type": "ConfigMonsterInitialPose"
    },
    "CrossBow_Fixed": {
      "$type": "ConfigMonsterInitialPose",
      "initialPoseID": 402,
      "initialPoseParams": {
        "$type": "ConfigPoseInitialParam",
        "boolParams": {
          "CrossBow_Fixed": "true"
        }
      }
    },
    "Sleep": {
      "$type": "ConfigMonsterInitialPose",
      "initialPoseID": 9002,
      "initialPoseParams": {
        "$type": "ConfigPoseInitialParam",
        "boolParams": {
          "Sleep": "true"
        }
      }
    },
    "Sit": {
      "$type": "ConfigMonsterInitialPose",
      "initialPoseID": 9003,
      "initialPoseParams": {
        "$type": "ConfigPoseInitialParam",
        "boolParams": {
          "Sit": "true"
        }
      }
    }
  },
  "aibeta": {
    "$type": "ConfigAIBeta",
    "enable": true,
    "moveSetting": {
      "$type": "ConfigAIMove",
      "navMeshAgentName": "Undead01",
      "almostReachedDistanceRun": 1.5
    },
    "sensing": {
      "$type": "ConfigAISensing",
      "settings": {
        "DefaultSetting": {
          "$type": "ConfigAISensingSetting",
          "feelRange": 8
        },
        "HighAlert": {
          "$type": "ConfigAISensingSetting",
          "viewRange": 40,
          "feelRange": 10
        },
        "Sleep": {
          "$type": "ConfigAISensingSetting",
          "viewRange": 0,
          "feelRange": 3
        },
        "Sit": {
          "$type": "ConfigAISensingSetting",
          "viewRange": 10
        }
      },
      "templates": {
        "DefaultTemplate": {
          "DefaultPoses": "DefaultSetting",
          "9002": "Sleep",
          "9003": "Sit"
        },
        "HighAlertTemplate": {
          "DefaultPoses": "HighAlert",
          "9002": "Sleep",
          "9003": "Sit"
        }
      }
    },
    "neurons": [
      "HIT"
    ],
    "threat": {
      "$type": "ConfigAIThreatSetting",
      "clearThreatByLostPath": true,
      "clearThreatTimerByDistance": 3,
      "viewAttenuation": [
        {
          "$type": "AIPoint",
          "x": 10,
          "y": 2
        },
        {
          "$type": "AIPoint",
          "x": 15,
          "y": 0.8
        },
        {
          "$type": "AIPoint",
          "x": 20,
          "y": 0.5
        },
        {
          "$type": "AIPoint",
          "x": 25,
          "y": 0.3
        },
        {
          "$type": "AIPoint",
          "x": 30,
          "y": 0.2
        }
      ]
    },
    "defendArea": {
      "$type": "ConfigAIDefendArea"
    },
    "profiling": {
      "$type": "ConfigAIProfilingSetting",
      "staticPoses": [
        9002,
        9003
      ]
    },
    "skills": {
      "103": {
        "$type": "ConfigAISkill",
        "name": "OnAlert",
        "skillType": "OnAlert",
        "faceTarget": true,
        "triggerGCD": false,
        "stateIDs": [
          "Life_Warning"
        ],
        "skillQueryingTime": 3
      },
      "104": {
        "$type": "ConfigAISkill",
        "name": "OnAlert",
        "skillType": "OnNerve",
        "faceTarget": true,
        "triggerGCD": false,
        "castCondition": {
          "$type": "ConfigAISkillCastCondition",
          "pose": [
            9002,
            9003
          ]
        },
        "nerveTrigger": [
          "HIT"
        ],
        "stateIDs": [
          "Life_Warning"
        ],
        "skillQueryingTime": 3
      },
      "111": {
        "$type": "ConfigAISkill",
        "name": "TurnToSleep",
        "skillType": "ActionPoint",
        "triggerGCD": false,
        "castCondition": {
          "$type": "ConfigAISkillCastCondition",
          "pose": [
            1,
            101,
            401,
            402,
            201,
            301
          ]
        },
        "stateIDs": [
          "TurnToSleep"
        ],
        "skillQueryingTime": 3
      },
      "112": {
        "$type": "ConfigAISkill",
        "name": "OutOfSleep",
        "skillType": "OnNerve",
        "triggerGCD": false,
        "castCondition": {
          "$type": "ConfigAISkillCastCondition",
          "pose": [
            9002
          ]
        },
        "nerveTrigger": [
          "AWAKE"
        ],
        "stateIDs": [
          "OutOfSleep"
        ],
        "skillQueryingTime": 3
      },
      "121": {
        "$type": "ConfigAISkill",
        "name": "TurnToSit",
        "skillType": "ActionPoint",
        "triggerGCD": false,
        "castCondition": {
          "$type": "ConfigAISkillCastCondition",
          "pose": [
            1,
            101,
            401,
            402,
            201,
            301
          ]
        },
        "stateIDs": [
          "TurnToSit"
        ],
        "skillQueryingTime": 3
      },
      "122": {
        "$type": "ConfigAISkill",
        "name": "OutOfSit",
        "skillType": "OnNerve",
        "triggerGCD": false,
        "castCondition": {
          "$type": "ConfigAISkillCastCondition",
          "pose": [
            9003
          ]
        },
        "nerveTrigger": [
          "AWAKE"
        ],
        "stateIDs": [
          "OutOfSit"
        ],
        "skillQueryingTime": 3
      },
      "123": {
        "$type": "ConfigAISkill",
        "name": "Talk_Sit",
        "skillType": "Free",
        "cd": 15,
        "cdUpperRange": 25,
        "initialCD": 15,
        "initialCDUpperRange": 25,
        "castCondition": {
          "$type": "ConfigAISkillCastCondition",
          "pose": [
            9003
          ]
        },
        "stateIDs": [
          "Life_Talk"
        ]
      },
      "124": {
        "$type": "ConfigAISkill",
        "name": "SleepFree01",
        "skillType": "Free",
        "cd": 15,
        "cdUpperRange": 25,
        "initialCD": 15,
        "initialCDUpperRange": 25,
        "castCondition": {
          "$type": "ConfigAISkillCastCondition",
          "pose": [
            9002
          ]
        },
        "stateIDs": [
          "SleepFree01"
        ]
      },
      "125": {
        "$type": "ConfigAISkill",
        "name": "SleepFree02",
        "skillType": "Free",
        "cd": 15,
        "cdUpperRange": 25,
        "initialCD": 15,
        "initialCDUpperRange": 25,
        "castCondition": {
          "$type": "ConfigAISkillCastCondition",
          "pose": [
            9002
          ]
        },
        "stateIDs": [
          "SleepFree02"
        ]
      },
      "126": {
        "$type": "ConfigAISkill",
        "name": "SleepFree03",
        "skillType": "Free",
        "cd": 15,
        "cdUpperRange": 25,
        "initialCD": 15,
        "initialCDUpperRange": 25,
        "castCondition": {
          "$type": "ConfigAISkillCastCondition",
          "pose": [
            9002
          ]
        },
        "stateIDs": [
          "SleepFree03"
        ]
      },
      "127": {
        "$type": "ConfigAISkill",
        "name": "SitFree01",
        "skillType": "Free",
        "cd": 15,
        "cdUpperRange": 15,
        "initialCD": 15,
        "initialCDUpperRange": 15,
        "castCondition": {
          "$type": "ConfigAISkillCastCondition",
          "pose": [
            9003
          ]
        },
        "stateIDs": [
          "SitFree01"
        ]
      },
      "201": {
        "$type": "ConfigAISkill",
        "name": "ThumpAttack",
        "priority": 2,
        "cd": 20,
        "cdUpperRange": 10,
        "initialCD": 10,
        "initialCDUpperRange": 10,
        "publicCDGroup": "meleeAttack_long",
        "castCondition": {
          "$type": "ConfigAISkillCastCondition",
          "pose": [
            1101
          ],
          "pickRangeMin": 2.75,
          "pickRangeMax": 5.25
        },
        "stateIDs": [
          "Sword_ThumpAttack"
        ]
      },
      "211": {
        "$type": "ConfigAISkill",
        "name": "NoWeapon_Attack",
        "cd": 3,
        "cdUpperRange": 1,
        "publicCDGroup": "meleeAttack",
        "enableSkillPrepare": true,
        "castCondition": {
          "$type": "ConfigAISkillCastCondition",
          "pose": [
            1001
          ],
          "pickRangeMin": 0.25,
          "pickRangeMax": 5.25,
          "castRangeMin": 1.25,
          "castRangeMax": 1.5
        },
        "stateIDs": [
          "NoWeapon_Attack"
        ]
      },
      "212": {
        "$type": "ConfigAISkill",
        "name": "NoWeapon_Attack",
        "isOutOfZoneSkill": true,
        "cd": 2.5,
        "cdUpperRange": 1,
        "publicCDGroup": "meleeAttack",
        "castCondition": {
          "$type": "ConfigAISkillCastCondition",
          "pose": [
            1001
          ],
          "pickRangeMax": 1.5
        },
        "stateIDs": [
          "NoWeapon_Attack"
        ]
      },
      "221": {
        "$type": "ConfigAISkill",
        "name": "SingleAttack",
        "priority": 4,
        "faceTarget": true,
        "cd": 3,
        "cdUpperRange": 1,
        "publicCDGroup": "meleeAttack",
        "castCondition": {
          "$type": "ConfigAISkillCastCondition",
          "pose": [
            1101
          ],
          "pickRangeMin": 1.5,
          "pickRangeMax": 3.25
        },
        "stateIDs": [
          "Sword_NormalAttack"
        ]
      },
      "222": {
        "$type": "ConfigAISkill",
        "name": "SingleAttack",
        "priority": 4,
        "faceTarget": true,
        "cd": 3.5,
        "cdUpperRange": 1.5,
        "publicCDGroup": "meleeAttack",
        "castCondition": {
          "$type": "ConfigAISkillCastCondition",
          "pose": [
            1301
          ],
          "pickRangeMin": 1.5,
          "pickRangeMax": 3
        },
        "stateIDs": [
          "Sword_NormalAttack"
        ]
      },
      "223": {
        "$type": "ConfigAISkill",
        "name": "SingleAttack",
        "priority": 4,
        "isOutOfZoneSkill": true,
        "faceTarget": true,
        "cd": 2.5,
        "cdUpperRange": 1,
        "publicCDGroup": "meleeAttack",
        "castCondition": {
          "$type": "ConfigAISkillCastCondition",
          "pose": [
            1101,
            1301
          ],
          "pickRangeMax": 2
        },
        "stateIDs": [
          "Sword_NormalAttack"
        ]
      },
      "231": {
        "$type": "ConfigAISkill",
        "name": "TripleAttack",
        "priority": 3,
        "cd": 10,
        "cdUpperRange": 10,
        "initialCD": 5,
        "initialCDUpperRange": 10,
        "publicCDGroup": "meleeAttack_long",
        "castCondition": {
          "$type": "ConfigAISkillCastCondition",
          "pose": [
            1101
          ],
          "pickRangeMax": 4.25
        },
        "stateIDs": [
          "Sword_TripleAttack"
        ]
      },
      "901": {
        "$type": "ConfigAISkill",
        "name": "Taunt",
        "isOutOfZoneSkill": true,
        "faceTarget": true,
        "cd": 1,
        "cdUpperRange": 3,
        "publicCDGroup": "RandomAction",
        "ignoreGCD": true,
        "triggerGCD": false,
        "castCondition": {
          "$type": "ConfigAISkillCastCondition",
          "pose": [
            1101,
            1301
          ],
          "targetAngleY": 45,
          "pickRangeMin": 2,
          "pickRangeMax": 10
        },
        "stateIDs": [
          "Taunt"
        ]
      },
      "902": {
        "$type": "ConfigAISkill",
        "name": "Taunt",
        "isUnreachableSkill": true,
        "faceTarget": true,
        "cd": 1,
        "cdUpperRange": 3,
        "publicCDGroup": "RandomAction",
        "ignoreGCD": true,
        "triggerGCD": false,
        "castCondition": {
          "$type": "ConfigAISkillCastCondition",
          "pose": [
            1101,
            1301
          ],
          "targetAngleY": 45,
          "pickRangeMax": 10
        },
        "stateIDs": [
          "Taunt"
        ]
      },
      "903": {
        "$type": "ConfigAISkill",
        "name": "Taunt",
        "isOutOfZoneSkill": true,
        "isUnreachableSkill": true,
        "faceTarget": true,
        "cd": 1,
        "cdUpperRange": 3,
        "publicCDGroup": "RandomAction",
        "ignoreGCD": true,
        "triggerGCD": false,
        "castCondition": {
          "$type": "ConfigAISkillCastCondition",
          "pose": [
            1101,
            1301
          ],
          "targetAngleY": 45,
          "pickRangeMax": 10
        },
        "stateIDs": [
          "Taunt"
        ]
      },
      "904": {
        "$type": "ConfigAISkill",
        "name": "Taunt",
        "priority": 2,
        "faceTarget": true,
        "cd": 5,
        "cdUpperRange": 10,
        "publicCDGroup": "RandomAction",
        "castCondition": {
          "$type": "ConfigAISkillCastCondition",
          "pose": [
            1101
          ],
          "targetAngleY": 45,
          "pickRangeMin": 6,
          "pickRangeMax": 30
        },
        "stateIDs": [
          "Taunt"
        ]
      },
      "905": {
        "$type": "ConfigAISkill",
        "name": "Taunt",
        "faceTarget": true,
        "cd": 2,
        "cdUpperRange": 5,
        "publicCDGroup": "RandomAction",
        "triggerGCD": false,
        "castCondition": {
          "$type": "ConfigAISkillCastCondition",
          "pose": [
            1101
          ],
          "targetAngleY": 45,
          "pickRangeMin": 3,
          "pickRangeMax": 6
        },
        "stateIDs": [
          "Taunt"
        ]
      },
      "906": {
        "$type": "ConfigAISkill",
        "name": "Taunt",
        "faceTarget": true,
        "cd": 15,
        "cdUpperRange": 15,
        "publicCDGroup": "RandomAction",
        "triggerGCD": false,
        "castCondition": {
          "$type": "ConfigAISkillCastCondition",
          "pose": [
            1301
          ],
          "targetAngleY": 45,
          "pickRangeMin": 3,
          "pickRangeMax": 6
        },
        "stateIDs": [
          "Taunt"
        ]
      },
      "911": {
        "$type": "ConfigAISkill",
        "name": "Taunt_NoWeapon",
        "isOutOfZoneSkill": true,
        "faceTarget": true,
        "cd": 1,
        "cdUpperRange": 3,
        "publicCDGroup": "RandomAction",
        "ignoreGCD": true,
        "triggerGCD": false,
        "castCondition": {
          "$type": "ConfigAISkillCastCondition",
          "pose": [
            1001
          ],
          "targetAngleY": 45,
          "pickRangeMin": 2,
          "pickRangeMax": 10
        },
        "stateIDs": [
          "Taunt_NoWeapon"
        ]
      },
      "912": {
        "$type": "ConfigAISkill",
        "name": "Taunt_NoWeapon",
        "isUnreachableSkill": true,
        "faceTarget": true,
        "cd": 1,
        "cdUpperRange": 3,
        "publicCDGroup": "RandomAction",
        "ignoreGCD": true,
        "triggerGCD": false,
        "castCondition": {
          "$type": "ConfigAISkillCastCondition",
          "pose": [
            1001
          ],
          "targetAngleY": 45,
          "pickRangeMax": 10
        },
        "stateIDs": [
          "Taunt_NoWeapon"
        ]
      },
      "913": {
        "$type": "ConfigAISkill",
        "name": "Taunt_NoWeapon",
        "isOutOfZoneSkill": true,
        "isUnreachableSkill": true,
        "faceTarget": true,
        "cd": 1,
        "cdUpperRange": 3,
        "publicCDGroup": "RandomAction",
        "ignoreGCD": true,
        "triggerGCD": false,
        "castCondition": {
          "$type": "ConfigAISkillCastCondition",
          "pose": [
            1001
          ],
          "targetAngleY": 45,
          "pickRangeMax": 10
        },
        "stateIDs": [
          "Taunt_NoWeapon"
        ]
      },
      "914": {
        "$type": "ConfigAISkill",
        "name": "Taunt_NoWeapon",
        "priority": 2,
        "faceTarget": true,
        "cd": 5,
        "cdUpperRange": 10,
        "publicCDGroup": "RandomAction",
        "castCondition": {
          "$type": "ConfigAISkillCastCondition",
          "pose": [
            1001
          ],
          "targetAngleY": 45,
          "pickRangeMin": 6,
          "pickRangeMax": 30
        },
        "stateIDs": [
          "Taunt_NoWeapon"
        ]
      },
      "915": {
        "$type": "ConfigAISkill",
        "name": "Taunt_NoWeapon",
        "faceTarget": true,
        "cd": 2,
        "cdUpperRange": 5,
        "publicCDGroup": "RandomAction",
        "triggerGCD": false,
        "castCondition": {
          "$type": "ConfigAISkillCastCondition",
          "pose": [
            1001
          ],
          "targetAngleY": 45,
          "pickRangeMin": 3,
          "pickRangeMax": 6
        },
        "stateIDs": [
          "Taunt_NoWeapon"
        ]
      },
      "601": {
        "$type": "ConfigAISkill",
        "name": "RangedAttack",
        "faceTarget": true,
        "cd": 3.5,
        "publicCDGroup": "rangedAttack",
        "castCondition": {
          "$type": "ConfigAISkillCastCondition",
          "pose": [
            1401,
            1402
          ],
          "pickRangeMax": 45
        },
        "stateIDs": [
          "Aim",
          "Shoot"
        ]
      },
      "602": {
        "$type": "ConfigAISkill",
        "name": "RangedAttack",
        "isOutOfZoneSkill": true,
        "faceTarget": true,
        "cd": 3.5,
        "publicCDGroup": "rangedAttack",
        "castCondition": {
          "$type": "ConfigAISkillCastCondition",
          "pose": [
            1401,
            1402
          ],
          "pickRangeMax": 45
        },
        "stateIDs": [
          "Aim",
          "Shoot"
        ]
      },
      "603": {
        "$type": "ConfigAISkill",
        "name": "RangedAttack",
        "isUnreachableSkill": true,
        "faceTarget": true,
        "cd": 3.5,
        "publicCDGroup": "rangedAttack",
        "castCondition": {
          "$type": "ConfigAISkillCastCondition",
          "pose": [
            1401,
            1402
          ],
          "pickRangeMax": 45
        },
        "stateIDs": [
          "Aim",
          "Shoot"
        ]
      },
      "604": {
        "$type": "ConfigAISkill",
        "name": "RangedAttack",
        "isOutOfZoneSkill": true,
        "isUnreachableSkill": true,
        "faceTarget": true,
        "cd": 3.5,
        "publicCDGroup": "rangedAttack",
        "castCondition": {
          "$type": "ConfigAISkillCastCondition",
          "pose": [
            1401,
            1402
          ],
          "pickRangeMax": 45
        },
        "stateIDs": [
          "Aim",
          "Shoot"
        ]
      },
      "301": {
        "$type": "ConfigAISkill",
        "name": "ThrowPebble",
        "cd": 5,
        "publicCDGroup": "rangedAttack",
        "castCondition": {
          "$type": "ConfigAISkillCastCondition",
          "pose": [
            1001
          ],
          "pickRangeMin": 4.25,
          "pickRangeMax": 15
        },
        "stateIDs": [
          "ThrowPebble"
        ]
      },
      "302": {
        "$type": "ConfigAISkill",
        "name": "ThrowPebble",
        "isOutOfZoneSkill": true,
        "cd": 5,
        "publicCDGroup": "rangedAttack",
        "castCondition": {
          "$type": "ConfigAISkillCastCondition",
          "pose": [
            1001
          ],
          "pickRangeMax": 15
        },
        "stateIDs": [
          "ThrowPebble"
        ]
      },
      "303": {
        "$type": "ConfigAISkill",
        "name": "ThrowPebble",
        "isUnreachableSkill": true,
        "cd": 5,
        "publicCDGroup": "rangedAttack",
        "castCondition": {
          "$type": "ConfigAISkillCastCondition",
          "pose": [
            1001
          ],
          "pickRangeMax": 15
        },
        "stateIDs": [
          "ThrowPebble"
        ]
      },
      "304": {
        "$type": "ConfigAISkill",
        "name": "ThrowPebble",
        "isOutOfZoneSkill": true,
        "isUnreachableSkill": true,
        "cd": 5,
        "publicCDGroup": "rangedAttack",
        "castCondition": {
          "$type": "ConfigAISkillCastCondition",
          "pose": [
            1001
          ],
          "pickRangeMax": 15
        },
        "stateIDs": [
          "ThrowPebble"
        ]
      },
      "311": {
        "$type": "ConfigAISkill",
        "name": "ThrowPebble_Shield",
        "cd": 5,
        "publicCDGroup": "rangedAttack",
        "castCondition": {
          "$type": "ConfigAISkillCastCondition",
          "pose": [
            1201
          ],
          "pickRangeMin": 4.25,
          "pickRangeMax": 15
        },
        "stateIDs": [
          "ThrowPebble_Shield"
        ]
      },
      "312": {
        "$type": "ConfigAISkill",
        "name": "ThrowPebble_Shield",
        "isOutOfZoneSkill": true,
        "cd": 5,
        "publicCDGroup": "rangedAttack",
        "castCondition": {
          "$type": "ConfigAISkillCastCondition",
          "pose": [
            1201
          ],
          "pickRangeMax": 15
        },
        "stateIDs": [
          "ThrowPebble_Shield"
        ]
      },
      "313": {
        "$type": "ConfigAISkill",
        "name": "ThrowPebble_Shield",
        "isUnreachableSkill": true,
        "cd": 5,
        "publicCDGroup": "rangedAttack",
        "castCondition": {
          "$type": "ConfigAISkillCastCondition",
          "pose": [
            1201
          ],
          "pickRangeMax": 15
        },
        "stateIDs": [
          "ThrowPebble_Shield"
        ]
      },
      "314": {
        "$type": "ConfigAISkill",
        "name": "ThrowPebble_Shield",
        "isOutOfZoneSkill": true,
        "isUnreachableSkill": true,
        "cd": 5,
        "publicCDGroup": "rangedAttack",
        "castCondition": {
          "$type": "ConfigAISkillCastCondition",
          "pose": [
            1201
          ],
          "pickRangeMax": 15
        },
        "stateIDs": [
          "ThrowPebble_Shield"
        ]
      }
    },
    "skillGCD": 3,
    "returnToBornTactic": {
      "$type": "ConfigAIReturnToBornPosSetting",
      "enable": true,
      "defaultSetting": {
        "$type": "ConfigAIReturnToBornPosData"
      }
    },
    "wanderTactic": {
      "$type": "ConfigAIWanderSetting",
      "enable": true,
      "condition": {
        "$type": "ConfigAITacticCondition",
        "pose": [
          1,
          101,
          401,
          201,
          301
        ]
      },
      "defaultSetting": {
        "$type": "ConfigAIWanderData",
        "cdMax": 3,
        "cdMin": 1.5,
        "distanceFromBorn": 15,
        "distanceFromCurrentMin": 3.75,
        "distanceFromCurrentMax": 7.5
      }
    },
    "investigateTactic": {
      "$type": "ConfigAIInvestigateSetting",
      "enable": true,
      "condition": {
        "$type": "ConfigAITacticCondition",
        "pose": [
          1,
          101,
          401,
          201,
          301
        ]
      }
    },
    "reactActionPointTactic": {
      "$type": "ConfigAIReactActionPointSetting",
      "enable": true,
      "defaultSetting": {
        "$type": "ConfigAIReactActionPointData",
        "reactList": [
          {
            "$type": "ConfigAIPickActionPointCriteria",
            "pointType": "SleepPoint",
            "pose": [
              1,
              101,
              401,
              402,
              201,
              301
            ],
            "nerveTrigger": [
              "ASLEEP"
            ],
            "skillID": 121
          }
        ]
      }
    },
    "meleeChargeTactic": {
      "$type": "ConfigAIMeleeChargeSetting",
      "enable": true,
      "condition": {
        "$type": "ConfigAITacticCondition",
        "pose": [
          1001,
          1101,
          1301,
          1201
        ]
      },
      "defaultSetting": {
        "$type": "ConfigAIMeleeChargeData",
        "startDistanceMin": 6,
        "startDistanceMax": 50,
        "stopDistance": 4.5,
        "innerDistance": 0
      }
    },
    "facingMoveTactic": {
      "$type": "ConfigAIFacingMoveSetting",
      "enable": true,
      "condition": {
        "$type": "ConfigAITacticCondition",
        "pose": [
          1001,
          1101,
          1401,
          1301,
          1201
        ]
      },
      "defaultSetting": {
        "$type": "ConfigAIFacingMoveData",
        "rangeMin": 2.5,
        "rangeMax": 4.5,
        "facingMoveWeight": {
          "$type": "ConfigAIFacingMoveWeight",
          "forward": 0,
          "back": 0,
          "left": 2,
          "right": 2
        }
      },
      "specification": {
        "1401": {
          "$type": "ConfigAIFacingMoveData",
          "rangeMin": 5,
          "rangeMax": 30,
          "facingMoveWeight": {
            "$type": "ConfigAIFacingMoveWeight",
            "forward": 0,
            "back": 0,
            "left": 0,
            "right": 0
          }
        },
        "1301": {
          "$type": "ConfigAIFacingMoveData",
          "rangeMax": 3,
          "facingMoveWeight": {
            "$type": "ConfigAIFacingMoveWeight",
            "forward": 0,
            "back": 0,
            "left": 2,
            "right": 2
          }
        }
      }
    }
  },
  "inputKeys": [
    {
      "$type": "ConfigKeyInput",
      "keyID": 201,
      "inputKeyCode": 257
    },
    {
      "$type": "ConfigKeyInput",
      "keyID": 231,
      "inputKeyCode": 258
    },
    {
      "$type": "ConfigKeyInput",
      "keyID": 211,
      "inputKeyCode": 259
    },
    {
      "$type": "ConfigKeyInput",
      "keyID": 601,
      "inputKeyCode": 260
    },
    {
      "$type": "ConfigKeyInput",
      "keyID": 221,
      "inputKeyCode": 262
    },
    {
      "$type": "ConfigKeyInput",
      "keyID": 901,
      "inputKeyCode": 261
    },
    {
      "$type": "ConfigKeyInput",
      "keyID": 301,
      "inputKeyCode": 264
    },
    {
      "$type": "ConfigKeyInput",
      "keyID": 311,
      "inputKeyCode": 265
    }
  ],
  "move": {
    "$type": "ConfigAnimatorMove",
    "facingMove": "FourDirection"
  },
  "audio": {
    "$type": "ConfigMonsterAudio",
    "animAudio": {
      "$type": "ConfigAnimationAudio",
      "onTransitionOut": [
        {
          "$type": "ConfigStateAudioEvent",
          "currentStateName": "Sword_TripleAttack",
          "audioEvent": {
            "$type": "ConfigWwiseString",
            "text": "Stop_sfx_monster_hili_club_tripleAttack"
          }
        },
        {
          "$type": "ConfigStateAudioEvent",
          "currentStateName": "Sword_ThumpAttack",
          "audioEvent": {
            "$type": "ConfigWwiseString",
            "text": "Stop_sfx_monster_hili_club_attack"
          }
        }
      ]
    },
    "randomVariantSwitchGroup": {
      "$type": "ConfigWwiseString"
    },
    "randomVariantSwitchValues": [
      {
        "$type": "ConfigWwiseString"
      }
    ]
  },
  "emojiBubble": {
    "$type": "ConfigEmojiBubble"
  }
}